{
  "n_episodes": 50,
  "horizon": 5,
  "top_k": 50,
  "wall_total_s": 140.98948001861572,
  "per_episode": [
    {
      "episode": 0,
      "total_reward": 227.32549179605877,
      "n_committed": 50,
      "budget_used": 132004.16437423447,
      "wall_s": 2.254312038421631
    },
    {
      "episode": 1,
      "total_reward": 227.2398895183892,
      "n_committed": 50,
      "budget_used": 131972.27478086055,
      "wall_s": 2.3618931770324707
    },
    {
      "episode": 2,
      "total_reward": 226.97708803181345,
      "n_committed": 50,
      "budget_used": 132014.79608,
      "wall_s": 2.4237849712371826
    },
    {
      "episode": 3,
      "total_reward": 227.22542325448367,
      "n_committed": 50,
      "budget_used": 131972.27478086055,
      "wall_s": 2.216094970703125
    },
    {
      "episode": 4,
      "total_reward": 226.08339172465136,
      "n_committed": 50,
      "budget_used": 132013.7680407855,
      "wall_s": 2.2438037395477295
    },
    {
      "episode": 5,
      "total_reward": 226.88568477876987,
      "n_committed": 50,
      "budget_used": 132004.16437423447,
      "wall_s": 2.3869829177856445
    },
    {
      "episode": 6,
      "total_reward": 226.95339842109328,
      "n_committed": 50,
      "budget_used": 131962.67111430952,
      "wall_s": 2.273736000061035
    },
    {
      "episode": 7,
      "total_reward": 227.2950918089317,
      "n_committed": 50,
      "budget_used": 131962.67111430955,
      "wall_s": 2.338318109512329
    },
    {
      "episode": 8,
      "total_reward": 227.73130690592916,
      "n_committed": 50,
      "budget_used": 131972.27478086055,
      "wall_s": 2.6484251022338867
    },
    {
      "episode": 9,
      "total_reward": 226.7918681945868,
      "n_committed": 50,
      "budget_used": 132004.16437423445,
      "wall_s": 2.6259541511535645
    },
    {
      "episode": 10,
      "total_reward": 227.2217872313262,
      "n_committed": 50,
      "budget_used": 131972.27478086055,
      "wall_s": 2.537044048309326
    },
    {
      "episode": 11,
      "total_reward": 226.61640962960374,
      "n_committed": 50,
      "budget_used": 132004.16437423447,
      "wall_s": 2.716606855392456
    },
    {
      "episode": 12,
      "total_reward": 226.74636836705923,
      "n_committed": 50,
      "budget_used": 131962.67111430952,
      "wall_s": 2.7002880573272705
    },
    {
      "episode": 13,
      "total_reward": 226.02484099770405,
      "n_committed": 50,
      "budget_used": 131963.699153524,
      "wall_s": 2.7207589149475098
    },
    {
      "episode": 14,
      "total_reward": 227.782933315581,
      "n_committed": 50,
      "budget_used": 131973.30282007504,
      "wall_s": 2.813523292541504
    },
    {
      "episode": 15,
      "total_reward": 227.44967661111852,
      "n_committed": 50,
      "budget_used": 131973.30282007504,
      "wall_s": 2.69433331489563
    },
    {
      "episode": 16,
      "total_reward": 226.47626778064568,
      "n_committed": 50,
      "budget_used": 132004.16437423447,
      "wall_s": 2.7845511436462402
    },
    {
      "episode": 17,
      "total_reward": 226.67204649870064,
      "n_committed": 50,
      "budget_used": 131973.30282007507,
      "wall_s": 2.6050970554351807
    },
    {
      "episode": 18,
      "total_reward": 226.71240877079586,
      "n_committed": 50,
      "budget_used": 132014.79608,
      "wall_s": 2.673214912414551
    },
    {
      "episode": 19,
      "total_reward": 227.4510028783492,
      "n_committed": 50,
      "budget_used": 131963.699153524,
      "wall_s": 2.7888216972351074
    },
    {
      "episode": 20,
      "total_reward": 227.1929070864133,
      "n_committed": 50,
      "budget_used": 131972.27478086055,
      "wall_s": 2.717573881149292
    },
    {
      "episode": 21,
      "total_reward": 227.54211383116174,
      "n_committed": 50,
      "budget_used": 131973.30282007507,
      "wall_s": 2.6398801803588867
    },
    {
      "episode": 22,
      "total_reward": 226.57766479467426,
      "n_committed": 50,
      "budget_used": 132014.79608,
      "wall_s": 2.7316269874572754
    },
    {
      "episode": 23,
      "total_reward": 226.79591093824848,
      "n_committed": 50,
      "budget_used": 131972.27478086055,
      "wall_s": 2.645087957382202
    },
    {
      "episode": 24,
      "total_reward": 225.85816484187657,
      "n_committed": 50,
      "budget_used": 131972.27478086058,
      "wall_s": 2.7994539737701416
    },
    {
      "episode": 25,
      "total_reward": 227.70009872246706,
      "n_committed": 50,
      "budget_used": 132004.16437423447,
      "wall_s": 2.651628017425537
    },
    {
      "episode": 26,
      "total_reward": 226.5942610121219,
      "n_committed": 50,
      "budget_used": 131972.27478086052,
      "wall_s": 2.66601300239563
    },
    {
      "episode": 27,
      "total_reward": 226.672180045605,
      "n_committed": 50,
      "budget_used": 132013.7680407855,
      "wall_s": 2.7271862030029297
    },
    {
      "episode": 28,
      "total_reward": 227.76815108837795,
      "n_committed": 50,
      "budget_used": 132014.79608,
      "wall_s": 2.8874659538269043
    },
    {
      "episode": 29,
      "total_reward": 226.9172660336473,
      "n_committed": 50,
      "budget_used": 132004.1643742345,
      "wall_s": 2.8852601051330566
    },
    {
      "episode": 30,
      "total_reward": 227.36291942870818,
      "n_committed": 50,
      "budget_used": 132005.192413449,
      "wall_s": 2.8644299507141113
    },
    {
      "episode": 31,
      "total_reward": 227.78368977228354,
      "n_committed": 50,
      "budget_used": 132014.79608,
      "wall_s": 2.996514081954956
    },
    {
      "episode": 32,
      "total_reward": 226.30362252362687,
      "n_committed": 50,
      "budget_used": 132013.7680407855,
      "wall_s": 2.957244873046875
    },
    {
      "episode": 33,
      "total_reward": 227.27031954499756,
      "n_committed": 50,
      "budget_used": 131972.27478086052,
      "wall_s": 3.0252089500427246
    },
    {
      "episode": 34,
      "total_reward": 227.0982075703929,
      "n_committed": 50,
      "budget_used": 131973.30282007504,
      "wall_s": 3.065903902053833
    },
    {
      "episode": 35,
      "total_reward": 225.91156249818906,
      "n_committed": 50,
      "budget_used": 131962.67111430955,
      "wall_s": 3.139070749282837
    },
    {
      "episode": 36,
      "total_reward": 227.60060008937177,
      "n_committed": 50,
      "budget_used": 132013.76804078548,
      "wall_s": 3.055497884750366
    },
    {
      "episode": 37,
      "total_reward": 227.47348692599272,
      "n_committed": 50,
      "budget_used": 131963.699153524,
      "wall_s": 3.094593048095703
    },
    {
      "episode": 38,
      "total_reward": 226.23049615391056,
      "n_committed": 50,
      "budget_used": 132014.79608,
      "wall_s": 3.102673053741455
    },
    {
      "episode": 39,
      "total_reward": 226.98921426770931,
      "n_committed": 50,
      "budget_used": 131972.27478086055,
      "wall_s": 3.1358518600463867
    },
    {
      "episode": 40,
      "total_reward": 225.71671443460542,
      "n_committed": 50,
      "budget_used": 131973.30282007504,
      "wall_s": 3.1637461185455322
    },
    {
      "episode": 41,
      "total_reward": 226.71764992510927,
      "n_committed": 50,
      "budget_used": 131962.67111430952,
      "wall_s": 2.9815521240234375
    },
    {
      "episode": 42,
      "total_reward": 225.8510003849786,
      "n_committed": 50,
      "budget_used": 131963.69915352407,
      "wall_s": 3.1614270210266113
    },
    {
      "episode": 43,
      "total_reward": 227.35569996818154,
      "n_committed": 50,
      "budget_used": 132013.76804078548,
      "wall_s": 3.3797800540924072
    },
    {
      "episode": 44,
      "total_reward": 225.7607489587742,
      "n_committed": 50,
      "budget_used": 131973.30282007507,
      "wall_s": 3.223273992538452
    },
    {
      "episode": 45,
      "total_reward": 226.680234360138,
      "n_committed": 50,
      "budget_used": 132014.79608,
      "wall_s": 3.2489237785339355
    },
    {
      "episode": 46,
      "total_reward": 227.42578382650584,
      "n_committed": 50,
      "budget_used": 131962.67111430952,
      "wall_s": 3.205940008163452
    },
    {
      "episode": 47,
      "total_reward": 227.39306362694688,
      "n_committed": 50,
      "budget_used": 131972.27478086055,
      "wall_s": 3.388678789138794
    },
    {
      "episode": 48,
      "total_reward": 225.97788056182347,
      "n_committed": 50,
      "budget_used": 132004.16437423445,
      "wall_s": 3.3230080604553223
    },
    {
      "episode": 49,
      "total_reward": 225.82031025575063,
      "n_committed": 50,
      "budget_used": 132005.19241344897,
      "wall_s": 3.3145248889923096
    }
  ],
  "best_so_far_curve": [
    227.32549179605877,
    227.32549179605877,
    227.32549179605877,
    227.32549179605877,
    227.32549179605877,
    227.32549179605877,
    227.32549179605877,
    227.32549179605877,
    227.73130690592916,
    227.73130690592916,
    227.73130690592916,
    227.73130690592916,
    227.73130690592916,
    227.73130690592916,
    227.782933315581,
    227.782933315581,
    227.782933315581,
    227.782933315581,
    227.782933315581,
    227.782933315581,
    227.782933315581,
    227.782933315581,
    227.782933315581,
    227.782933315581,
    227.782933315581,
    227.782933315581,
    227.782933315581,
    227.782933315581,
    227.782933315581,
    227.782933315581,
    227.782933315581,
    227.78368977228354,
    227.78368977228354,
    227.78368977228354,
    227.78368977228354,
    227.78368977228354,
    227.78368977228354,
    227.78368977228354,
    227.78368977228354,
    227.78368977228354,
    227.78368977228354,
    227.78368977228354,
    227.78368977228354,
    227.78368977228354,
    227.78368977228354,
    227.78368977228354,
    227.78368977228354,
    227.78368977228354,
    227.78368977228354,
    227.78368977228354
  ],
  "stats": {
    "best": 227.78368977228354,
    "mean": 226.88008599976365,
    "std": 0.6030607510293426,
    "median": 226.93533222737028
  }
}